mlflow_server_proxy/__init__.py
mlflow_server_proxy/icons/mlflow.svg
mlflow_server_proxy/tests/__init__.py
mlflow_server_proxy/tests/test_setup.py
mlflow_server_proxy-0.1.0.dist-info/LICENSE.txt
mlflow_server_proxy-0.1.0.dist-info/METADATA
mlflow_server_proxy-0.1.0.dist-info/WHEEL
mlflow_server_proxy-0.1.0.dist-info/entry_points.txt
mlflow_server_proxy-0.1.0.dist-info/top_level.txt
mlflow_server_proxy-0.1.0.dist-info/RECORD
