Metadata-Version: 2.1
Name: mlflow-server-proxy
Version: 0.1.0
Summary: Jupyter server proxy extension for mlflow tracking server
Home-page: https://github.com/americanexpress/mlflow-server-proxy
Author: American Express
License: Apache 2.0 license
Keywords: jupyter,mlflow,jupyterhub
Platform: UNKNOWN
Requires-Dist: jupyter-server-proxy
Provides-Extra: dev
Requires-Dist: autopep8 ; extra == 'dev'
Requires-Dist: pytest ; extra == 'dev'
Requires-Dist: flake8 ; extra == 'dev'
Requires-Dist: pytest-cov (>=2.6.1) ; extra == 'dev'
Requires-Dist: mock ; extra == 'dev'
Provides-Extra: resources
Requires-Dist: mlflow ; extra == 'resources'
